{
  "_class": "symbolInstance",
  "booleanOperation": 0,
  "do_objectID": "BC87E579-D7E1-48D4-8354-B2A5A8FA52E6",
  "exportOptions": {
    "_class": "exportOptions",
    "do_objectID": "B90808B2-4CBC-48AB-A600-128F4E249CCB",
    "exportFormats": [
    ],
    "includedLayerIds": [
    ],
    "layerOptions": 0,
    "shouldTrim": false
  },
  "frame": {
    "_class": "rect",
    "constrainProportions": false,
    "do_objectID": "A81A7F0F-2E0D-448F-A841-596A657FC8A1",
    "height": 48,
    "width": 236,
    "x": 150,
    "y": 214
  },
  "horizontalSpacing": 0,
  "isFixedToViewport": false,
  "isFlippedHorizontal": false,
  "isFlippedVertical": false,
  "isLocked": false,
  "isVisible": true,
  "layerListExpandedType": 0,
  "name": "button.primary",
  "nameIsFixed": true,
  "overrideValues": [
    {
      "_class": "overrideValue",
      "do_objectID": "4575C910-9CA7-415D-9726-91B6870DE75A",
      "overrideName": "9D830137-0D3A-4B4B-BBA9-926AC1304D4F_stringValue",
      "value": "Submit"
    }
  ],
  "resizingConstraint": 63,
  "resizingType": 0,
  "rotation": 0,
  "scale": 1,
  "shouldBreakMaskChain": false,
  "style": {
    "_class": "style",
    "do_objectID": "DAA1A83B-F23C-4B5E-87F4-55A110C7ECA7",
    "endMarkerType": 0,
    "miterLimit": 10,
    "startMarkerType": 0,
    "windingRule": 1
  },
  "symbolID": "0E161BFB-7A48-4BCF-B8AC-DD776E41AE0D",
  "userInfo": {
    "com.animaapp.stc-sketch-plugin": {
      "kModelPropertiesKey": {
      }
    }
  },
  "verticalSpacing": 0
}