{
  "_class": "group",
  "booleanOperation": -1,
  "do_objectID": "F8087D68-0C6E-4FA2-8C14-B49E542B779A",
  "exportOptions": {
    "_class": "exportOptions",
    "exportFormats": [
    ],
    "includedLayerIds": [
    ],
    "layerOptions": 0,
    "shouldTrim": false
  },
  "frame": {
    "_class": "rect",
    "constrainProportions": false,
    "height": 48,
    "width": 236,
    "x": 0,
    "y": 0
  },
  "hasClickThrough": true,
  "isFixedToViewport": false,
  "isFlippedHorizontal": false,
  "isFlippedVertical": false,
  "isLocked": false,
  "isVisible": true,
  "layerListExpandedType": 0,
  "layers": [
    {
      "class": "shapeGroup",
      "id": "52A2EACB-5F3F-4722-A254-483DCB21F502"
    },
    {
      "class": "text",
      "id": "9B888F6F-DEF7-4E6F-B3D1-E2D0CFA54DC9"
    }
  ],
  "name": "button.primary hover",
  "nameIsFixed": false,
  "resizingConstraint": 63,
  "resizingType": 0,
  "rotation": 0,
  "shouldBreakMaskChain": false,
  "style": {
    "_class": "style",
    "endMarkerType": 0,
    "miterLimit": 10,
    "startMarkerType": 0,
    "windingRule": 1
  },
  "userInfo": {
    "com.animaapp.stc-sketch-plugin": {
      "kModelPropertiesKey": {
      }
    }
  }
}